WrikePy/__init__.py
WrikePy/helpers.py
WrikePy/wrikepy.py
WrikePy-1.0.4.dist-info/LICENSE.txt
WrikePy-1.0.4.dist-info/METADATA
WrikePy-1.0.4.dist-info/WHEEL
WrikePy-1.0.4.dist-info/top_level.txt
WrikePy-1.0.4.dist-info/RECORD
