Metadata-Version: 2.1
Name: WrikePy
Version: 1.0.4
Summary: A Python wrapper for the Wrike API.
Home-page: https://github.com/TGoers-FNSB/WrikePy
Author: T. Goers
Author-email: tristan.goers@fnsb.gov
Project-URL: Bug Tracker, https://github.com/TGoers-FNSB/WrikePy/issues
Classifier: Programming Language :: Python :: 3
Classifier: License :: OSI Approved :: MIT License
Classifier: Operating System :: OS Independent
Requires-Python: >=3.6
License-File: LICENSE.txt
